baleapi/__init__.py
baleapi/bot.py
baleapi/client.py
baleapi/errors.py
baleapi/keyboard.py
baleapi/message.py
baleapi/types.py
baleapi/utils.py
baleapi-2.2.0.dist-info/licenses/LICENSE
baleapi-2.2.0.dist-info/METADATA
baleapi-2.2.0.dist-info/WHEEL
baleapi-2.2.0.dist-info/top_level.txt
baleapi-2.2.0.dist-info/RECORD
