Metadata-Version: 2.4
Name: baleapi
Version: 2.2.0
Summary: Python library for Bale Bot API
Home-page: https://github.com/iTs-GoJo/bale
Author: Ali-Jafari
Author-email: thealiapi@gmail.com
Classifier: Programming Language :: Python :: 3
Classifier: License :: OSI Approved :: MIT License
Classifier: Operating System :: OS Independent
Requires-Python: >=3.8
License-File: LICENSE
Requires-Dist: aiohttp>=3.8.5
Dynamic: author
Dynamic: author-email
Dynamic: classifier
Dynamic: description
Dynamic: description-content-type
Dynamic: home-page
Dynamic: license-file
Dynamic: requires-dist
Dynamic: requires-python
Dynamic: summary
